convoy/__init__.py
convoy/convoy.py
convoy/data.py
convoy/api/__init__.py
convoy/api/delivery_attempts.py
convoy/api/endpoint.py
convoy/api/event.py
convoy/api/event_delivery.py
convoy/api/group.py
convoy/api/source.py
convoy/api/subscription.py
convoy/client/__init__.py
convoy/client/client.py
convoy/utils/__init__.py
convoy/utils/helpers.py
convoy/utils/webhook.py
convoy_python-0.2.0.dist-info/LICENSE
convoy_python-0.2.0.dist-info/METADATA
convoy_python-0.2.0.dist-info/WHEEL
convoy_python-0.2.0.dist-info/top_level.txt
convoy_python-0.2.0.dist-info/RECORD
