Metadata-Version: 2.1
Name: convoy-python
Version: 0.2.0
Summary: Python SDK for Convoy
Home-page: https://github.com/frain-dev/convoy-python
Author: Frain Inc.
Author-email: info@frain.dev
License: MIT
Classifier: License :: OSI Approved :: MIT License
Classifier: Programming Language :: Python
Classifier: Programming Language :: Python :: 3
License-File: LICENSE
Requires-Dist: requests
